PySense/PySense.py
PySense/PySenseAuthentication.py
PySense/PySenseBloxAction.py
PySense/PySenseBranding.py
PySense/PySenseBuildTask.py
PySense/PySenseConnection.py
PySense/PySenseDashboard.py
PySense/PySenseDataModel.py
PySense/PySenseDataSet.py
PySense/PySenseElasticube.py
PySense/PySenseException.py
PySense/PySenseFolder.py
PySense/PySenseGroup.py
PySense/PySensePlugin.py
PySense/PySenseRestConnector.py
PySense/PySenseRule.py
PySense/PySenseTable.py
PySense/PySenseUser.py
PySense/PySenseUtils.py
PySense/PySenseWidget.py
PySense/SisenseRole.py
PySense/SisenseVersion.py
PySense/__init__.py
PySense/PySenseMixIns/BrandingMixIn.py
PySense/PySenseMixIns/ConnectionMixIn.py
PySense/PySenseMixIns/DashboardMixIn.py
PySense/PySenseMixIns/DataModelMixIn.py
PySense/PySenseMixIns/ElasticubeMixIn.py
PySense/PySenseMixIns/FolderMixIn.py
PySense/PySenseMixIns/GroupMixIn.py
PySense/PySenseMixIns/PluginMixIn.py
PySense/PySenseMixIns/RoleMixIn.py
PySense/PySenseMixIns/SettingsMixIn.py
PySense/PySenseMixIns/UserMixIn.py
PySense/PySenseMixIns/__init__.py
PySenseSDK-1.0.7.dist-info/LICENSE
PySenseSDK-1.0.7.dist-info/METADATA
PySenseSDK-1.0.7.dist-info/WHEEL
PySenseSDK-1.0.7.dist-info/top_level.txt
PySenseSDK-1.0.7.dist-info/RECORD
