Metadata-Version: 2.1
Name: PySenseSDK
Version: 1.0.7
Summary: Sisense Python SDK
Home-page: https://github.com/nathangiusti/PySense
Author: Nathan Giusti
Author-email: nathanggiusti@gmail.com
Classifier: Programming Language :: Python :: 3
Classifier: License :: OSI Approved :: GNU General Public License v3 (GPLv3)
Classifier: Operating System :: OS Independent
Requires-Python: >=3.6
License-File: LICENSE
Requires-Dist: requests
Requires-Dist: PyYAML
